derp/__init__.py
derp/__main__.py
derp/application.py
derp/deprecation.py
derp/main.py
derp/version_number.py
derp/walker.py
derp-0.1.1.dist-info/LICENSE
derp-0.1.1.dist-info/METADATA
derp-0.1.1.dist-info/WHEEL
derp-0.1.1.dist-info/entry_points.txt
derp-0.1.1.dist-info/top_level.txt
derp-0.1.1.dist-info/RECORD
