Metadata-Version: 2.1
Name: derp
Version: 0.1.1
Summary: command line tool to ensure that deprecated code is removed in a timely manner
Home-page: https://github.com/bfolie/derp
Author: Brendan Folie
Author-email: bfolie@citrine.io
License: MIT
Platform: UNKNOWN
Classifier: Development Status :: 2 - Pre-Alpha
Classifier: Environment :: Console
Classifier: Programming Language :: Python
Classifier: Programming Language :: Python :: 3.5
Classifier: Programming Language :: Python :: 3.6
Classifier: Programming Language :: Python :: 3.7
Classifier: Programming Language :: Python :: 3.8
Classifier: Intended Audience :: Developers
